Contributors
LICENSE
README.md
skick/__init__.py
skick/abstract_hash.py
skick/actor.py
skick/addressing.py
skick/back_actor.py
skick/cluster.py
skick/combined_message.py
skick/conversation.py
skick/directory.py
skick/front_actor.py
skick/info_bucket.py
skick/message_system_interface.py
skick/plain_websocket.py
skick/rabbit_message.py
skick/rate_limiter.py
skick/redis_hash.py
skick/routed_message.py
skick/shard.py
skick/simple_hash.py
skick/simple_message.py
skick/skick.py
skick/syzygy.py
skick/terminate.py
skick/websocket_actor.py
skick/websocket_interface.py
skick-0.0.1a0.dev1.dist-info/METADATA
skick-0.0.1a0.dev1.dist-info/WHEEL
skick-0.0.1a0.dev1.dist-info/licenses/LICENSE
skick-0.0.1a0.dev1.dist-info/RECORD
