Metadata-Version: 2.1
Name: skick
Version: 0.0.1a0.dev1
Summary: Skick is a library for building actor based web application backends that communicate with javascript clients over websockets. It is in an early state of development.
Project-URL: Documentation, https://github.com/webyda/skick#readme
Project-URL: Issues, https://github.com/webyda/skick/issues
Project-URL: Source, https://github.com/webyda/skick
Author-email: Wennströms byrå för datateknik AB <adrian@webyda.se>
Maintainer-email: Adrian Wennström <adrian@webyda.se>
License-File: LICENSE
Keywords: actor,actor model,asyncio,rabbitmq,websockets
Classifier: Development Status :: 2 - Pre-Alpha
Classifier: Intended Audience :: Developers
Classifier: Intended Audience :: Information Technology
Classifier: License :: OSI Approved :: MIT License
Classifier: Programming Language :: Python
Classifier: Programming Language :: Python :: 3.10
Classifier: Programming Language :: Python :: 3.11
Classifier: Programming Language :: Python :: Implementation :: CPython
Classifier: Topic :: Internet
Classifier: Topic :: Internet :: WWW/HTTP :: Dynamic Content
Classifier: Topic :: Software Development :: Libraries
Classifier: Topic :: Software Development :: Libraries :: Application Frameworks
Requires-Python: >=3.10
Requires-Dist: aio-pika>=8
Requires-Dist: orjson>=3
Requires-Dist: redis>=4
Requires-Dist: schema>=0.7
Requires-Dist: uvloop>=0.16; platform_system != 'Windows'
Requires-Dist: websockets>=10
